[
  {
    "value": 3576,
    "icon": "https://d3ejb2l5e3bvmc.cloudfront.net/game-images/microgaming/4704/thumbnail.jpg",
    "name": "Mask of Amun"
  },
  {
    "value": 4134,
    "icon": "https://d3ejb2l5e3bvmc.cloudfront.net/game-images/microgaming/4725/thumbnail.jpg",
    "name": "Bolt X Up™"
  },
  {
    "value": 4608,
    "icon": "https://d3ejb2l5e3bvmc.cloudfront.net/game-images/microgaming/4726/thumbnail.jpg",
    "name": "777 Surge™"
  },
  {
    "value": 2175,
    "icon": "https://d3ejb2l5e3bvmc.cloudfront.net/game-images/microgaming/4246/thumbnail.jpg",
    "name": "Lucky Twins Wilds"
  },
  {
    "value": 2413,
    "icon": "https://d3ejb2l5e3bvmc.cloudfront.net/game-images/microgaming/4025/thumbnail.jpg",
    "name": "Ancient Fortunes: Poseidon Megaways ™"
  },
  {
    "value": 4985,
    "icon": "https://d3ejb2l5e3bvmc.cloudfront.net/game-images/microgaming/4076/thumbnail.jpg",
    "name": "Break Away Deluxe"
  },
  {
    "value": 3735,
    "icon": "https://d3ejb2l5e3bvmc.cloudfront.net/game-images/microgaming/4699/thumbnail.jpg",
    "name": "Fishin' Pots of Gold"
  },
  {
    "value": 2141,
    "icon": "https://d3ejb2l5e3bvmc.cloudfront.net/game-images/microgaming/4026/thumbnail.jpg",
    "name": "Ancient Fortunes: Zeus"
  },
  {
    "value": 3668,
    "icon": "https://d3ejb2l5e3bvmc.cloudfront.net/game-images/microgaming/4009/thumbnail.jpg",
    "name": "Africa X UP™"
  },
  {
    "value": 2616,
    "icon": "https://d3ejb2l5e3bvmc.cloudfront.net/game-images/microgaming/4077/thumbnail.jpg",
    "name": "Break Away Lucky Wilds"
  },
  {
    "value": 3718,
    "icon": "https://d3ejb2l5e3bvmc.cloudfront.net/game-images/microgaming/4102/thumbnail.jpg",
    "name": "Chronicles of Olympus X UP"
  },
  {
    "value": 4599,
    "icon": "https://d3ejb2l5e3bvmc.cloudfront.net/game-images/microgaming/3985/thumbnail.jpg",
    "name": "10000 Wishes"
  },
  {
    "value": 3995,
    "icon": "https://d3ejb2l5e3bvmc.cloudfront.net/game-images/microgaming/4287/thumbnail.jpg",
    "name": "Queen of Alexandria™"
  },
  {
    "value": 3042,
    "icon": "https://d3ejb2l5e3bvmc.cloudfront.net/game-images/microgaming/4037/thumbnail.jpg",
    "name": "Aurora Wilds"
  },
  {
    "value": 4367,
    "icon": "https://d3ejb2l5e3bvmc.cloudfront.net/game-images/microgaming/4245/thumbnail.jpg",
    "name": "Lucky Twins Jackpot"
  },
  {
    "value": 2460,
    "icon": "https://d3ejb2l5e3bvmc.cloudfront.net/game-images/microgaming/3993/thumbnail.jpg",
    "name": "777 Mega Deluxe™"
  },
  {
    "value": 2278,
    "icon": "https://d3ejb2l5e3bvmc.cloudfront.net/game-images/microgaming/4195/thumbnail.jpg",
    "name": "Immortal Romance"
  },
  {
    "value": 2168,
    "icon": "https://d3ejb2l5e3bvmc.cloudfront.net/game-images/microgaming/4223/thumbnail.jpg",
    "name": "Lara Croft: Temples and Tombs"
  },
  {
    "value": 3954,
    "icon": "https://d3ejb2l5e3bvmc.cloudfront.net/game-images/microgaming/4191/thumbnail.jpg",
    "name": "Hyper Gold"
  },
  {
    "value": 4418,
    "icon": "https://d3ejb2l5e3bvmc.cloudfront.net/game-images/microgaming/3997/thumbnail.jpg",
    "name": "9 Masks Of Fire"
  },
  {
    "value": 4119,
    "icon": "https://d3ejb2l5e3bvmc.cloudfront.net/game-images/microgaming/4108/thumbnail.jpg",
    "name": "Cossacks: The Wild Hunt"
  },
  {
    "value": 3440,
    "icon": "https://d3ejb2l5e3bvmc.cloudfront.net/game-images/microgaming/4084/thumbnail.jpg",
    "name": "Break Da Bank Again™ MEGAWAYS™"
  },
  {
    "value": 4370,
    "icon": "https://d3ejb2l5e3bvmc.cloudfront.net/game-images/microgaming/4021/thumbnail.jpg",
    "name": "Amazing Link Zeus"
  },
  {
    "value": 4149,
    "icon": "https://d3ejb2l5e3bvmc.cloudfront.net/game-images/microgaming/4062/thumbnail.jpg",
    "name": "Blazing Mammoth"
  },
  {
    "value": 4267,
    "icon": "https://d3ejb2l5e3bvmc.cloudfront.net/game-images/microgaming/4031/thumbnail.jpg",
    "name": "Assassin Moon"
  },
  {
    "value": 2795,
    "icon": "https://d3ejb2l5e3bvmc.cloudfront.net/game-images/microgaming/3990/thumbnail.jpg",
    "name": "4 Diamond Blues™ - Megaways™"
  },
  {
    "value": 4807,
    "icon": "https://d3ejb2l5e3bvmc.cloudfront.net/game-images/microgaming/4315/thumbnail.jpg",
    "name": "Rugby Star Deluxe"
  },
  {
    "value": 2140,
    "icon": "https://d3ejb2l5e3bvmc.cloudfront.net/game-images/microgaming/4404/thumbnail.jpg",
    "name": "WWE Legends: Link & Win"
  },
  {
    "value": 2073,
    "icon": "https://d3ejb2l5e3bvmc.cloudfront.net/game-images/microgaming/4050/thumbnail.jpg",
    "name": "Basketball Star"
  },
  {
    "value": 4912,
    "icon": "https://d3ejb2l5e3bvmc.cloudfront.net/game-images/microgaming/4036/thumbnail.jpg",
    "name": "Augustus"
  },
  {
    "value": 3066,
    "icon": "https://d3ejb2l5e3bvmc.cloudfront.net/game-images/microgaming/4022/thumbnail.jpg",
    "name": "Amazing Link™ Apollo"
  },
  {
    "value": 3656,
    "icon": "https://d3ejb2l5e3bvmc.cloudfront.net/game-images/microgaming/4079/thumbnail.jpg",
    "name": "Break Away Ultra"
  },
  {
    "value": 3200,
    "icon": "https://d3ejb2l5e3bvmc.cloudfront.net/game-images/microgaming/4075/thumbnail.jpg",
    "name": "Break Away"
  },
  {
    "value": 4552,
    "icon": "https://d3ejb2l5e3bvmc.cloudfront.net/game-images/microgaming/4326/thumbnail.jpg",
    "name": "Shogun of Time"
  },
  {
    "value": 4527,
    "icon": "https://d3ejb2l5e3bvmc.cloudfront.net/game-images/microgaming/4333/thumbnail.jpg",
    "name": "Sisters of Oz: Jackpots"
  },
  {
    "value": 3557,
    "icon": "https://d3ejb2l5e3bvmc.cloudfront.net/game-images/microgaming/4373/thumbnail.jpg",
    "name": "Thunderstruck Wild Lightning"
  },
  {
    "value": 3757,
    "icon": "https://d3ejb2l5e3bvmc.cloudfront.net/game-images/microgaming/4144/thumbnail.jpg",
    "name": "Emperor of the Sea Deluxe"
  },
  {
    "value": 3423,
    "icon": "https://d3ejb2l5e3bvmc.cloudfront.net/game-images/microgaming/3996/thumbnail.jpg",
    "name": "9 Blazing Diamonds"
  },
  {
    "value": 2617,
    "icon": "https://d3ejb2l5e3bvmc.cloudfront.net/game-images/microgaming/4383/thumbnail.jpg",
    "name": "Treasures of Lion City"
  },
  {
    "value": 2116,
    "icon": "https://d3ejb2l5e3bvmc.cloudfront.net/game-images/microgaming/4280/thumbnail.jpg",
    "name": "Playboy Fortunes"
  },
  {
    "value": 3859,
    "icon": "https://d3ejb2l5e3bvmc.cloudfront.net/game-images/microgaming/4155/thumbnail.jpg",
    "name": "Football Star Deluxe"
  },
  {
    "value": 2707,
    "icon": "https://d3ejb2l5e3bvmc.cloudfront.net/game-images/microgaming/4134/thumbnail.jpg",
    "name": "Dragon's Breath"
  },
  {
    "value": 3096,
    "icon": "https://d3ejb2l5e3bvmc.cloudfront.net/game-images/microgaming/4279/thumbnail.jpg",
    "name": "Playboy"
  },
  {
    "value": 3039,
    "icon": "https://d3ejb2l5e3bvmc.cloudfront.net/game-images/microgaming/3986/thumbnail.jpg",
    "name": "108 Heroes"
  },
  {
    "value": 2051,
    "icon": "https://d3ejb2l5e3bvmc.cloudfront.net/game-images/microgaming/3987/thumbnail.jpg",
    "name": "108 Heroes Multiplier Fortunes"
  },
  {
    "value": 3545,
    "icon": "https://d3ejb2l5e3bvmc.cloudfront.net/game-images/microgaming/3991/thumbnail.jpg",
    "name": "5 Reel Drive"
  },
  {
    "value": 3050,
    "icon": "https://d3ejb2l5e3bvmc.cloudfront.net/game-images/microgaming/3992/thumbnail.jpg",
    "name": "5 Star Knockout"
  },
  {
    "value": 2884,
    "icon": "https://d3ejb2l5e3bvmc.cloudfront.net/game-images/microgaming/3994/thumbnail.jpg",
    "name": "777 Royal Wheel"
  },
  {
    "value": 4053,
    "icon": "https://d3ejb2l5e3bvmc.cloudfront.net/game-images/microgaming/3995/thumbnail.jpg",
    "name": "8 Golden Skulls of the Holly Roger Megaways™"
  },
  {
    "value": 4958,
    "icon": "https://d3ejb2l5e3bvmc.cloudfront.net/game-images/microgaming/3998/thumbnail.jpg",
    "name": "9 Masks of Fire™ HyperSpins™"
  },
  {
    "value": 2951,
    "icon": "https://d3ejb2l5e3bvmc.cloudfront.net/game-images/microgaming/3999/thumbnail.jpg",
    "name": "9 Pots of Gold"
  },
  {
    "value": 2631,
    "icon": "https://d3ejb2l5e3bvmc.cloudfront.net/game-images/microgaming/4000/thumbnail.jpg",
    "name": "A Dark Matter"
  },
  {
    "value": 3442,
    "icon": "https://d3ejb2l5e3bvmc.cloudfront.net/game-images/microgaming/4001/thumbnail.jpg",
    "name": "A Tale of Elves"
  },
  {
    "value": 4447,
    "icon": "https://d3ejb2l5e3bvmc.cloudfront.net/game-images/microgaming/4006/thumbnail.jpg",
    "name": "ActionOps Snow and Sable"
  },
  {
    "value": 2519,
    "icon": "https://d3ejb2l5e3bvmc.cloudfront.net/game-images/microgaming/4007/thumbnail.jpg",
    "name": "Adventure Palace"
  },
  {
    "value": 3291,
    "icon": "https://d3ejb2l5e3bvmc.cloudfront.net/game-images/microgaming/4008/thumbnail.jpg",
    "name": "Adventures Of Doubloon Island"
  },
  {
    "value": 4261,
    "icon": "https://d3ejb2l5e3bvmc.cloudfront.net/game-images/microgaming/4010/thumbnail.jpg",
    "name": "Age of Conquest"
  },
  {
    "value": 3301,
    "icon": "https://d3ejb2l5e3bvmc.cloudfront.net/game-images/microgaming/4011/thumbnail.jpg",
    "name": "Age Of Discovery"
  },
  {
    "value": 2580,
    "icon": "https://d3ejb2l5e3bvmc.cloudfront.net/game-images/microgaming/4012/thumbnail.jpg",
    "name": "Agent Jane Blonde"
  },
  {
    "value": 3477,
    "icon": "https://d3ejb2l5e3bvmc.cloudfront.net/game-images/microgaming/4013/thumbnail.jpg",
    "name": "Agent Jane Blonde Max Volume"
  },
  {
    "value": 2536,
    "icon": "https://d3ejb2l5e3bvmc.cloudfront.net/game-images/microgaming/4014/thumbnail.jpg",
    "name": "Agent Jane Blonde Returns"
  },
  {
    "value": 4107,
    "icon": "https://d3ejb2l5e3bvmc.cloudfront.net/game-images/microgaming/4015/thumbnail.jpg",
    "name": "Alaskan Fishing"
  },
  {
    "value": 3069,
    "icon": "https://d3ejb2l5e3bvmc.cloudfront.net/game-images/microgaming/4016/thumbnail.jpg",
    "name": "Alchemist Stone"
  },
  {
    "value": 3956,
    "icon": "https://d3ejb2l5e3bvmc.cloudfront.net/game-images/microgaming/4018/thumbnail.jpg",
    "name": "Alchemy Fortunes"
  },
  {
    "value": 3266,
    "icon": "https://d3ejb2l5e3bvmc.cloudfront.net/game-images/microgaming/4028/thumbnail.jpg",
    "name": "Arctic Enchantress"
  },
  {
    "value": 4788,
    "icon": "https://d3ejb2l5e3bvmc.cloudfront.net/game-images/microgaming/4029/thumbnail.jpg",
    "name": "Ariana"
  },
  {
    "value": 2499,
    "icon": "https://d3ejb2l5e3bvmc.cloudfront.net/game-images/microgaming/4030/thumbnail.jpg",
    "name": "Asian Beauty"
  },
  {
    "value": 3205,
    "icon": "https://d3ejb2l5e3bvmc.cloudfront.net/game-images/microgaming/4032/thumbnail.jpg",
    "name": "Astro Legends: Lyra and Erion"
  },
  {
    "value": 2081,
    "icon": "https://d3ejb2l5e3bvmc.cloudfront.net/game-images/microgaming/4035/thumbnail.jpg",
    "name": "Atlantis Rising"
  },
  {
    "value": 3727,
    "icon": "https://d3ejb2l5e3bvmc.cloudfront.net/game-images/microgaming/4039/thumbnail.jpg",
    "name": "Avalon"
  },
  {
    "value": 4947,
    "icon": "https://d3ejb2l5e3bvmc.cloudfront.net/game-images/microgaming/4046/thumbnail.jpg",
    "name": "Badminton Hero"
  },
  {
    "value": 2992,
    "icon": "https://d3ejb2l5e3bvmc.cloudfront.net/game-images/microgaming/4047/thumbnail.jpg",
    "name": "Banana Odyssey"
  },
  {
    "value": 4684,
    "icon": "https://d3ejb2l5e3bvmc.cloudfront.net/game-images/microgaming/4048/thumbnail.jpg",
    "name": "Bar Bar Black Sheep 5 Reel"
  },
  {
    "value": 3329,
    "icon": "https://d3ejb2l5e3bvmc.cloudfront.net/game-images/microgaming/4049/thumbnail.jpg",
    "name": "Bars And Stripes"
  },
  {
    "value": 3040,
    "icon": "https://d3ejb2l5e3bvmc.cloudfront.net/game-images/microgaming/4051/thumbnail.jpg",
    "name": "Basketball Star Deluxe"
  },
  {
    "value": 4022,
    "icon": "https://d3ejb2l5e3bvmc.cloudfront.net/game-images/microgaming/4053/thumbnail.jpg",
    "name": "Basketball Star Wilds"
  },
  {
    "value": 3455,
    "icon": "https://d3ejb2l5e3bvmc.cloudfront.net/game-images/microgaming/4054/thumbnail.jpg",
    "name": "Battle Royale"
  },
  {
    "value": 3331,
    "icon": "https://d3ejb2l5e3bvmc.cloudfront.net/game-images/microgaming/4055/thumbnail.jpg",
    "name": "Beach Babes"
  },
  {
    "value": 2338,
    "icon": "https://d3ejb2l5e3bvmc.cloudfront.net/game-images/microgaming/4057/thumbnail.jpg",
    "name": "Big Boom Riches"
  },
  {
    "value": 4697,
    "icon": "https://d3ejb2l5e3bvmc.cloudfront.net/game-images/microgaming/4058/thumbnail.jpg",
    "name": "Big Kahuna"
  },
  {
    "value": 3412,
    "icon": "https://d3ejb2l5e3bvmc.cloudfront.net/game-images/microgaming/4059/thumbnail.jpg",
    "name": "Big Top"
  },
  {
    "value": 2454,
    "icon": "https://d3ejb2l5e3bvmc.cloudfront.net/game-images/microgaming/4061/thumbnail.jpg",
    "name": "Bikini Party"
  },
  {
    "value": 2347,
    "icon": "https://d3ejb2l5e3bvmc.cloudfront.net/game-images/microgaming/4063/thumbnail.jpg",
    "name": "Boat of Fortune"
  },
  {
    "value": 3564,
    "icon": "https://d3ejb2l5e3bvmc.cloudfront.net/game-images/microgaming/4068/thumbnail.jpg",
    "name": "Boogie Monsters"
  },
  {
    "value": 3883,
    "icon": "https://d3ejb2l5e3bvmc.cloudfront.net/game-images/microgaming/4069/thumbnail.jpg",
    "name": "Book of King Arthur"
  },
  {
    "value": 2226,
    "icon": "https://d3ejb2l5e3bvmc.cloudfront.net/game-images/microgaming/4070/thumbnail.jpg",
    "name": "Book Of Mrs Claus"
  },
  {
    "value": 4230,
    "icon": "https://d3ejb2l5e3bvmc.cloudfront.net/game-images/microgaming/4071/thumbnail.jpg",
    "name": "Book of Oz"
  },
  {
    "value": 3219,
    "icon": "https://d3ejb2l5e3bvmc.cloudfront.net/game-images/microgaming/4072/thumbnail.jpg",
    "name": "Book of Oz Lock 'N Spin"
  },
  {
    "value": 3632,
    "icon": "https://d3ejb2l5e3bvmc.cloudfront.net/game-images/microgaming/4073/thumbnail.jpg",
    "name": "Bookie of Odds"
  },
  {
    "value": 3125,
    "icon": "https://d3ejb2l5e3bvmc.cloudfront.net/game-images/microgaming/4074/thumbnail.jpg",
    "name": "Boom Pirates"
  },
  {
    "value": 4007,
    "icon": "https://d3ejb2l5e3bvmc.cloudfront.net/game-images/microgaming/4081/thumbnail.jpg",
    "name": "Break da Bank"
  },
  {
    "value": 4178,
    "icon": "https://d3ejb2l5e3bvmc.cloudfront.net/game-images/microgaming/4082/thumbnail.jpg",
    "name": "Break da Bank Again"
  },
  {
    "value": 4792,
    "icon": "https://d3ejb2l5e3bvmc.cloudfront.net/game-images/microgaming/4083/thumbnail.jpg",
    "name": "Break da Bank Again Respin"
  },
  {
    "value": 4096,
    "icon": "https://d3ejb2l5e3bvmc.cloudfront.net/game-images/microgaming/4085/thumbnail.jpg",
    "name": "Bridesmaids"
  },
  {
    "value": 3041,
    "icon": "https://d3ejb2l5e3bvmc.cloudfront.net/game-images/microgaming/4086/thumbnail.jpg",
    "name": "Burning Desire"
  },
  {
    "value": 4955,
    "icon": "https://d3ejb2l5e3bvmc.cloudfront.net/game-images/microgaming/4087/thumbnail.jpg",
    "name": "Bush Telegraph"
  },
  {
    "value": 2403,
    "icon": "https://d3ejb2l5e3bvmc.cloudfront.net/game-images/microgaming/4088/thumbnail.jpg",
    "name": "Bust the Bank"
  },
  {
    "value": 3930,
    "icon": "https://d3ejb2l5e3bvmc.cloudfront.net/game-images/microgaming/4089/thumbnail.jpg",
    "name": "Bust The Mansion"
  },
  {
    "value": 3561,
    "icon": "https://d3ejb2l5e3bvmc.cloudfront.net/game-images/microgaming/4090/thumbnail.jpg",
    "name": "Candy Dreams"
  },
  {
    "value": 4177,
    "icon": "https://d3ejb2l5e3bvmc.cloudfront.net/game-images/microgaming/4091/thumbnail.jpg",
    "name": "Carnaval"
  },
  {
    "value": 4378,
    "icon": "https://d3ejb2l5e3bvmc.cloudfront.net/game-images/microgaming/4094/thumbnail.jpg",
    "name": "Cash Crazy"
  },
  {
    "value": 4940,
    "icon": "https://d3ejb2l5e3bvmc.cloudfront.net/game-images/microgaming/4095/thumbnail.jpg",
    "name": "Cash of Kingdoms"
  },
  {
    "value": 3688,
    "icon": "https://d3ejb2l5e3bvmc.cloudfront.net/game-images/microgaming/4096/thumbnail.jpg",
    "name": "Cashapillar"
  },
  {
    "value": 3263,
    "icon": "https://d3ejb2l5e3bvmc.cloudfront.net/game-images/microgaming/4099/thumbnail.jpg",
    "name": "Cat Clans"
  },
  {
    "value": 3921,
    "icon": "https://d3ejb2l5e3bvmc.cloudfront.net/game-images/microgaming/4100/thumbnail.jpg",
    "name": "Centre Court"
  },
  {
    "value": 4055,
    "icon": "https://d3ejb2l5e3bvmc.cloudfront.net/game-images/microgaming/4101/thumbnail.jpg",
    "name": "Chicago Gold"
  },
  {
    "value": 3146,
    "icon": "https://d3ejb2l5e3bvmc.cloudfront.net/game-images/microgaming/4103/thumbnail.jpg",
    "name": "Classic 243"
  },
  {
    "value": 4088,
    "icon": "https://d3ejb2l5e3bvmc.cloudfront.net/game-images/microgaming/4106/thumbnail.jpg",
    "name": "Cool Buck - 5 Reel"
  },
  {
    "value": 3237,
    "icon": "https://d3ejb2l5e3bvmc.cloudfront.net/game-images/microgaming/4107/thumbnail.jpg",
    "name": "Cool Wolf"
  },
  {
    "value": 2184,
    "icon": "https://d3ejb2l5e3bvmc.cloudfront.net/game-images/microgaming/4109/thumbnail.jpg",
    "name": "Couch Potato"
  },
  {
    "value": 3848,
    "icon": "https://d3ejb2l5e3bvmc.cloudfront.net/game-images/microgaming/4110/thumbnail.jpg",
    "name": "Crazy Chameleons"
  },
  {
    "value": 3684,
    "icon": "https://d3ejb2l5e3bvmc.cloudfront.net/game-images/microgaming/4111/thumbnail.jpg",
    "name": "Cricket Star"
  },
  {
    "value": 4906,
    "icon": "https://d3ejb2l5e3bvmc.cloudfront.net/game-images/microgaming/4112/thumbnail.jpg",
    "name": "Cricket Star Scratch"
  },
  {
    "value": 3251,
    "icon": "https://d3ejb2l5e3bvmc.cloudfront.net/game-images/microgaming/4114/thumbnail.jpg",
    "name": "deadmau5"
  },
  {
    "value": 3509,
    "icon": "https://d3ejb2l5e3bvmc.cloudfront.net/game-images/microgaming/4115/thumbnail.jpg",
    "name": "Deck the Halls"
  },
  {
    "value": 3607,
    "icon": "https://d3ejb2l5e3bvmc.cloudfront.net/game-images/microgaming/4116/thumbnail.jpg",
    "name": "Deco Diamonds"
  },
  {
    "value": 2248,
    "icon": "https://d3ejb2l5e3bvmc.cloudfront.net/game-images/microgaming/4122/thumbnail.jpg",
    "name": "Diamond Empire"
  },
  {
    "value": 4735,
    "icon": "https://d3ejb2l5e3bvmc.cloudfront.net/game-images/microgaming/4123/thumbnail.jpg",
    "name": "Diamond King Jackpots"
  },
  {
    "value": 4911,
    "icon": "https://d3ejb2l5e3bvmc.cloudfront.net/game-images/microgaming/4124/thumbnail.jpg",
    "name": "Divine Diamonds"
  },
  {
    "value": 4173,
    "icon": "https://d3ejb2l5e3bvmc.cloudfront.net/game-images/microgaming/4125/thumbnail.jpg",
    "name": "Doki Doki Parfait"
  },
  {
    "value": 3590,
    "icon": "https://d3ejb2l5e3bvmc.cloudfront.net/game-images/microgaming/4127/thumbnail.jpg",
    "name": "Dolphin Quest"
  },
  {
    "value": 2290,
    "icon": "https://d3ejb2l5e3bvmc.cloudfront.net/game-images/microgaming/4131/thumbnail.jpg",
    "name": "Double Wammy"
  },
  {
    "value": 2892,
    "icon": "https://d3ejb2l5e3bvmc.cloudfront.net/game-images/microgaming/4132/thumbnail.jpg",
    "name": "Dragon Dance"
  },
  {
    "value": 2910,
    "icon": "https://d3ejb2l5e3bvmc.cloudfront.net/game-images/microgaming/4133/thumbnail.jpg",
    "name": "Dragon Shard"
  },
  {
    "value": 3627,
    "icon": "https://d3ejb2l5e3bvmc.cloudfront.net/game-images/microgaming/4135/thumbnail.jpg",
    "name": "Dragonz"
  },
  {
    "value": 4594,
    "icon": "https://d3ejb2l5e3bvmc.cloudfront.net/game-images/microgaming/4136/thumbnail.jpg",
    "name": "Dream Date"
  },
  {
    "value": 4822,
    "icon": "https://d3ejb2l5e3bvmc.cloudfront.net/game-images/microgaming/4138/thumbnail.jpg",
    "name": "Eagle's Wings"
  },
  {
    "value": 4489,
    "icon": "https://d3ejb2l5e3bvmc.cloudfront.net/game-images/microgaming/4139/thumbnail.jpg",
    "name": "Egyptian Tombs"
  },
  {
    "value": 4171,
    "icon": "https://d3ejb2l5e3bvmc.cloudfront.net/game-images/microgaming/4140/thumbnail.jpg",
    "name": "Elven Gold"
  },
  {
    "value": 4386,
    "icon": "https://d3ejb2l5e3bvmc.cloudfront.net/game-images/microgaming/4141/thumbnail.jpg",
    "name": "Emerald Gold"
  },
  {
    "value": 2149,
    "icon": "https://d3ejb2l5e3bvmc.cloudfront.net/game-images/microgaming/4142/thumbnail.jpg",
    "name": "EmotiCoins"
  },
  {
    "value": 3982,
    "icon": "https://d3ejb2l5e3bvmc.cloudfront.net/game-images/microgaming/4143/thumbnail.jpg",
    "name": "Emperor Of The Sea"
  },
  {
    "value": 4501,
    "icon": "https://d3ejb2l5e3bvmc.cloudfront.net/game-images/microgaming/4149/thumbnail.jpg",
    "name": "Exotic Cats"
  },
  {
    "value": 3000,
    "icon": "https://d3ejb2l5e3bvmc.cloudfront.net/game-images/microgaming/4150/thumbnail.jpg",
    "name": "Fire Forge"
  },
  {
    "value": 2471,
    "icon": "https://d3ejb2l5e3bvmc.cloudfront.net/game-images/microgaming/4151/thumbnail.jpg",
    "name": "Fish Party"
  },
  {
    "value": 4265,
    "icon": "https://d3ejb2l5e3bvmc.cloudfront.net/game-images/microgaming/4153/thumbnail.jpg",
    "name": "Flower Fortunes Asia"
  },
  {
    "value": 2535,
    "icon": "https://d3ejb2l5e3bvmc.cloudfront.net/game-images/microgaming/4154/thumbnail.jpg",
    "name": "Football Star"
  },
  {
    "value": 2169,
    "icon": "https://d3ejb2l5e3bvmc.cloudfront.net/game-images/microgaming/4156/thumbnail.jpg",
    "name": "Forbidden Throne"
  },
  {
    "value": 2744,
    "icon": "https://d3ejb2l5e3bvmc.cloudfront.net/game-images/microgaming/4160/thumbnail.jpg",
    "name": "Fortune Girl"
  },
  {
    "value": 2883,
    "icon": "https://d3ejb2l5e3bvmc.cloudfront.net/game-images/microgaming/4161/thumbnail.jpg",
    "name": "Fortune Rush"
  },
  {
    "value": 3052,
    "icon": "https://d3ejb2l5e3bvmc.cloudfront.net/game-images/microgaming/4162/thumbnail.jpg",
    "name": "Fortunium"
  },
  {
    "value": 2146,
    "icon": "https://d3ejb2l5e3bvmc.cloudfront.net/game-images/microgaming/4164/thumbnail.jpg",
    "name": "Fruit Blast"
  },
  {
    "value": 4849,
    "icon": "https://d3ejb2l5e3bvmc.cloudfront.net/game-images/microgaming/4165/thumbnail.jpg",
    "name": "Fruit vs Candy"
  },
  {
    "value": 2153,
    "icon": "https://d3ejb2l5e3bvmc.cloudfront.net/game-images/microgaming/4166/thumbnail.jpg",
    "name": "Gems And Dragons"
  },
  {
    "value": 4184,
    "icon": "https://d3ejb2l5e3bvmc.cloudfront.net/game-images/microgaming/4167/thumbnail.jpg",
    "name": "Gems Odyssey"
  },
  {
    "value": 4755,
    "icon": "https://d3ejb2l5e3bvmc.cloudfront.net/game-images/microgaming/4168/thumbnail.jpg",
    "name": "Girls With Guns - Jungle Heat"
  },
  {
    "value": 3890,
    "icon": "https://d3ejb2l5e3bvmc.cloudfront.net/game-images/microgaming/4169/thumbnail.jpg",
    "name": "Gnome Wood"
  },
  {
    "value": 2229,
    "icon": "https://d3ejb2l5e3bvmc.cloudfront.net/game-images/microgaming/4170/thumbnail.jpg",
    "name": "Gold Collector"
  },
  {
    "value": 2041,
    "icon": "https://d3ejb2l5e3bvmc.cloudfront.net/game-images/microgaming/4172/thumbnail.jpg",
    "name": "Gold Factory"
  },
  {
    "value": 3221,
    "icon": "https://d3ejb2l5e3bvmc.cloudfront.net/game-images/microgaming/4173/thumbnail.jpg",
    "name": "Goldaur Guardians"
  },
  {
    "value": 2676,
    "icon": "https://d3ejb2l5e3bvmc.cloudfront.net/game-images/microgaming/4174/thumbnail.jpg",
    "name": "Golden Era"
  },
  {
    "value": 4852,
    "icon": "https://d3ejb2l5e3bvmc.cloudfront.net/game-images/microgaming/4175/thumbnail.jpg",
    "name": "Golden Princess"
  },
  {
    "value": 3288,
    "icon": "https://d3ejb2l5e3bvmc.cloudfront.net/game-images/microgaming/4176/thumbnail.jpg",
    "name": "Golden Stallion"
  },
  {
    "value": 3385,
    "icon": "https://d3ejb2l5e3bvmc.cloudfront.net/game-images/microgaming/4177/thumbnail.jpg",
    "name": "Gopher Gold"
  },
  {
    "value": 4621,
    "icon": "https://d3ejb2l5e3bvmc.cloudfront.net/game-images/microgaming/4178/thumbnail.jpg",
    "name": "Halloweenies"
  },
  {
    "value": 3754,
    "icon": "https://d3ejb2l5e3bvmc.cloudfront.net/game-images/microgaming/4179/thumbnail.jpg",
    "name": "Happy Holidays"
  },
  {
    "value": 3472,
    "icon": "https://d3ejb2l5e3bvmc.cloudfront.net/game-images/microgaming/4180/thumbnail.jpg",
    "name": "Happy Monster Claw"
  },
  {
    "value": 3104,
    "icon": "https://d3ejb2l5e3bvmc.cloudfront.net/game-images/microgaming/4181/thumbnail.jpg",
    "name": "Harveys"
  },
  {
    "value": 3660,
    "icon": "https://d3ejb2l5e3bvmc.cloudfront.net/game-images/microgaming/4184/thumbnail.jpg",
    "name": "High Society"
  },
  {
    "value": 3090,
    "icon": "https://d3ejb2l5e3bvmc.cloudfront.net/game-images/microgaming/4186/thumbnail.jpg",
    "name": "Hippie Days"
  },
  {
    "value": 4015,
    "icon": "https://d3ejb2l5e3bvmc.cloudfront.net/game-images/microgaming/4187/thumbnail.jpg",
    "name": "Holly Jolly Penguins"
  },
  {
    "value": 4050,
    "icon": "https://d3ejb2l5e3bvmc.cloudfront.net/game-images/microgaming/4190/thumbnail.jpg",
    "name": "Huangdi - The Yellow Emperor"
  },
  {
    "value": 2655,
    "icon": "https://d3ejb2l5e3bvmc.cloudfront.net/game-images/microgaming/4192/thumbnail.jpg",
    "name": "Hyper Star"
  },
  {
    "value": 2109,
    "icon": "https://d3ejb2l5e3bvmc.cloudfront.net/game-images/microgaming/4193/thumbnail.jpg",
    "name": "Hyper Strike HyperSpins"
  },
  {
    "value": 3363,
    "icon": "https://d3ejb2l5e3bvmc.cloudfront.net/game-images/microgaming/4194/thumbnail.jpg",
    "name": "Hyper Strike™"
  },
  {
    "value": 4384,
    "icon": "https://d3ejb2l5e3bvmc.cloudfront.net/game-images/microgaming/4198/thumbnail.jpg",
    "name": "Ingots of Cai Shen"
  },
  {
    "value": 3064,
    "icon": "https://d3ejb2l5e3bvmc.cloudfront.net/game-images/microgaming/4199/thumbnail.jpg",
    "name": "Isis"
  },
  {
    "value": 4469,
    "icon": "https://d3ejb2l5e3bvmc.cloudfront.net/game-images/microgaming/4205/thumbnail.jpg",
    "name": "Joyful Joker Megaways"
  },
  {
    "value": 2410,
    "icon": "https://d3ejb2l5e3bvmc.cloudfront.net/game-images/microgaming/4206/thumbnail.jpg",
    "name": "Jungle Jim - El Dorado"
  },
  {
    "value": 2604,
    "icon": "https://d3ejb2l5e3bvmc.cloudfront.net/game-images/microgaming/4207/thumbnail.jpg",
    "name": "Jungle Jim and the Lost Sphinx"
  },
  {
    "value": 4652,
    "icon": "https://d3ejb2l5e3bvmc.cloudfront.net/game-images/microgaming/4208/thumbnail.jpg",
    "name": "Jurassic Park Gold"
  },
  {
    "value": 2203,
    "icon": "https://d3ejb2l5e3bvmc.cloudfront.net/game-images/microgaming/4209/thumbnail.jpg",
    "name": "Jurassic World"
  },
  {
    "value": 4182,
    "icon": "https://d3ejb2l5e3bvmc.cloudfront.net/game-images/microgaming/4211/thumbnail.jpg",
    "name": "Karaoke Party"
  },
  {
    "value": 3940,
    "icon": "https://d3ejb2l5e3bvmc.cloudfront.net/game-images/microgaming/4212/thumbnail.jpg",
    "name": "Kathmandu"
  },
  {
    "value": 4634,
    "icon": "https://d3ejb2l5e3bvmc.cloudfront.net/game-images/microgaming/4214/thumbnail.jpg",
    "name": "King Tusk"
  },
  {
    "value": 3357,
    "icon": "https://d3ejb2l5e3bvmc.cloudfront.net/game-images/microgaming/4215/thumbnail.jpg",
    "name": "Kings Of Cash"
  },
  {
    "value": 4313,
    "icon": "https://d3ejb2l5e3bvmc.cloudfront.net/game-images/microgaming/4216/thumbnail.png",
    "name": "Kings of Crystals"
  },
  {
    "value": 4543,
    "icon": "https://d3ejb2l5e3bvmc.cloudfront.net/game-images/microgaming/4217/thumbnail.jpg",
    "name": "Kitty Cabana"
  },
  {
    "value": 4996,
    "icon": "https://d3ejb2l5e3bvmc.cloudfront.net/game-images/microgaming/4218/thumbnail.jpg",
    "name": "Kodiak Kingdom"
  },
  {
    "value": 2730,
    "icon": "https://d3ejb2l5e3bvmc.cloudfront.net/game-images/microgaming/4219/thumbnail.jpg",
    "name": "Ladies Nite"
  },
  {
    "value": 3082,
    "icon": "https://d3ejb2l5e3bvmc.cloudfront.net/game-images/microgaming/4220/thumbnail.jpg",
    "name": "Ladies Nite 2 Turn Wild"
  },
  {
    "value": 3686,
    "icon": "https://d3ejb2l5e3bvmc.cloudfront.net/game-images/microgaming/4222/thumbnail.jpg",
    "name": "Lady In Red"
  },
  {
    "value": 4584,
    "icon": "https://d3ejb2l5e3bvmc.cloudfront.net/game-images/microgaming/4224/thumbnail.jpg",
    "name": "Legacy of Oz ™"
  },
  {
    "value": 4991,
    "icon": "https://d3ejb2l5e3bvmc.cloudfront.net/game-images/microgaming/4225/thumbnail.jpg",
    "name": "Legend of the Moon Lovers"
  },
  {
    "value": 2542,
    "icon": "https://d3ejb2l5e3bvmc.cloudfront.net/game-images/microgaming/4226/thumbnail.jpg",
    "name": "Life Of Riches"
  },
  {
    "value": 2364,
    "icon": "https://d3ejb2l5e3bvmc.cloudfront.net/game-images/microgaming/4227/thumbnail.jpg",
    "name": "Lion's Pride"
  },
  {
    "value": 4488,
    "icon": "https://d3ejb2l5e3bvmc.cloudfront.net/game-images/microgaming/4228/thumbnail.jpg",
    "name": "Liquid Gold"
  },
  {
    "value": 4648,
    "icon": "https://d3ejb2l5e3bvmc.cloudfront.net/game-images/microgaming/4229/thumbnail.jpg",
    "name": "Loaded"
  },
  {
    "value": 3596,
    "icon": "https://d3ejb2l5e3bvmc.cloudfront.net/game-images/microgaming/4230/thumbnail.jpg",
    "name": "Long Mu Fortunes"
  },
  {
    "value": 3113,
    "icon": "https://d3ejb2l5e3bvmc.cloudfront.net/game-images/microgaming/4232/thumbnail.jpg",
    "name": "Lucha Legends"
  },
  {
    "value": 4127,
    "icon": "https://d3ejb2l5e3bvmc.cloudfront.net/game-images/microgaming/4233/thumbnail.jpg",
    "name": "Lucky Bachelors"
  },
  {
    "value": 3049,
    "icon": "https://d3ejb2l5e3bvmc.cloudfront.net/game-images/microgaming/4234/thumbnail.jpg",
    "name": "Lucky Clucks"
  },
  {
    "value": 2941,
    "icon": "https://d3ejb2l5e3bvmc.cloudfront.net/game-images/microgaming/4235/thumbnail.jpg",
    "name": "Lucky Firecracker"
  },
  {
    "value": 3973,
    "icon": "https://d3ejb2l5e3bvmc.cloudfront.net/game-images/microgaming/4236/thumbnail.jpg",
    "name": "Lucky Koi"
  },
  {
    "value": 2078,
    "icon": "https://d3ejb2l5e3bvmc.cloudfront.net/game-images/microgaming/4238/thumbnail.jpg",
    "name": "Lucky Leprechaun"
  },
  {
    "value": 3821,
    "icon": "https://d3ejb2l5e3bvmc.cloudfront.net/game-images/microgaming/4239/thumbnail.jpg",
    "name": "Lucky Little Gods"
  },
  {
    "value": 4166,
    "icon": "https://d3ejb2l5e3bvmc.cloudfront.net/game-images/microgaming/4240/thumbnail.jpg",
    "name": "Lucky Riches Hyperspins"
  },
  {
    "value": 4710,
    "icon": "https://d3ejb2l5e3bvmc.cloudfront.net/game-images/microgaming/4244/thumbnail.jpg",
    "name": "Lucky Twins Catcher"
  },
  {
    "value": 4242,
    "icon": "https://d3ejb2l5e3bvmc.cloudfront.net/game-images/microgaming/4249/thumbnail.jpg",
    "name": "Magic of Sahara"
  },
  {
    "value": 4502,
    "icon": "https://d3ejb2l5e3bvmc.cloudfront.net/game-images/microgaming/4251/thumbnail.jpg",
    "name": "Maui Mischief"
  },
  {
    "value": 2861,
    "icon": "https://d3ejb2l5e3bvmc.cloudfront.net/game-images/microgaming/4253/thumbnail.jpg",
    "name": "Mayan Princess"
  },
  {
    "value": 4319,
    "icon": "https://d3ejb2l5e3bvmc.cloudfront.net/game-images/microgaming/4254/thumbnail.jpg",
    "name": "Mega Money Multiplier"
  },
  {
    "value": 2034,
    "icon": "https://d3ejb2l5e3bvmc.cloudfront.net/game-images/microgaming/4255/thumbnail.jpg",
    "name": "Mega Money Rush"
  },
  {
    "value": 3035,
    "icon": "https://d3ejb2l5e3bvmc.cloudfront.net/game-images/microgaming/4257/thumbnail.jpg",
    "name": "Mermaids Millions"
  },
  {
    "value": 4873,
    "icon": "https://d3ejb2l5e3bvmc.cloudfront.net/game-images/microgaming/4258/thumbnail.jpg",
    "name": "Moby Dick"
  },
  {
    "value": 4969,
    "icon": "https://d3ejb2l5e3bvmc.cloudfront.net/game-images/microgaming/4259/thumbnail.jpg",
    "name": "Monster Blast"
  },
  {
    "value": 2999,
    "icon": "https://d3ejb2l5e3bvmc.cloudfront.net/game-images/microgaming/4260/thumbnail.jpg",
    "name": "Monster Wheels"
  },
  {
    "value": 2013,
    "icon": "https://d3ejb2l5e3bvmc.cloudfront.net/game-images/microgaming/4262/thumbnail.jpg",
    "name": "Munchkins"
  },
  {
    "value": 3356,
    "icon": "https://d3ejb2l5e3bvmc.cloudfront.net/game-images/microgaming/4263/thumbnail.jpg",
    "name": "Mystic Dreams"
  },
  {
    "value": 3664,
    "icon": "https://d3ejb2l5e3bvmc.cloudfront.net/game-images/microgaming/4264/thumbnail.jpg",
    "name": "Neptune's Riches: Ocean of Wilds"
  },
  {
    "value": 4122,
    "icon": "https://d3ejb2l5e3bvmc.cloudfront.net/game-images/microgaming/4266/thumbnail.jpg",
    "name": "Noble Sky"
  },
  {
    "value": 2305,
    "icon": "https://d3ejb2l5e3bvmc.cloudfront.net/game-images/microgaming/4267/thumbnail.jpg",
    "name": "Odin's Riches"
  },
  {
    "value": 4664,
    "icon": "https://d3ejb2l5e3bvmc.cloudfront.net/game-images/microgaming/4268/thumbnail.jpg",
    "name": "Oink Country Love"
  },
  {
    "value": 2411,
    "icon": "https://d3ejb2l5e3bvmc.cloudfront.net/game-images/microgaming/4270/thumbnail.jpg",
    "name": "Oni Hunter Night Sakura"
  },
  {
    "value": 2419,
    "icon": "https://d3ejb2l5e3bvmc.cloudfront.net/game-images/microgaming/4272/thumbnail.jpg",
    "name": "Our Days"
  },
  {
    "value": 2836,
    "icon": "https://d3ejb2l5e3bvmc.cloudfront.net/game-images/microgaming/4273/thumbnail.jpg",
    "name": "Party Island"
  },
  {
    "value": 3600,
    "icon": "https://d3ejb2l5e3bvmc.cloudfront.net/game-images/microgaming/4274/thumbnail.jpg",
    "name": "Peek-a-Boo - 5 Reel"
  },
  {
    "value": 3232,
    "icon": "https://d3ejb2l5e3bvmc.cloudfront.net/game-images/microgaming/4275/thumbnail.jpg",
    "name": "Pets Go Wild"
  },
  {
    "value": 4046,
    "icon": "https://d3ejb2l5e3bvmc.cloudfront.net/game-images/microgaming/4277/thumbnail.jpg",
    "name": "Ping Pong Star"
  },
  {
    "value": 4618,
    "icon": "https://d3ejb2l5e3bvmc.cloudfront.net/game-images/microgaming/4278/thumbnail.jpg",
    "name": "Pistoleras"
  },
  {
    "value": 4659,
    "icon": "https://d3ejb2l5e3bvmc.cloudfront.net/game-images/microgaming/4281/thumbnail.jpg",
    "name": "Playboy Gold"
  },
  {
    "value": 4085,
    "icon": "https://d3ejb2l5e3bvmc.cloudfront.net/game-images/microgaming/4282/thumbnail.jpg",
    "name": "Playboy Gold Jackpots"
  },
  {
    "value": 3966,
    "icon": "https://d3ejb2l5e3bvmc.cloudfront.net/game-images/microgaming/4283/thumbnail.jpg",
    "name": "Poke The Guy"
  },
  {
    "value": 4840,
    "icon": "https://d3ejb2l5e3bvmc.cloudfront.net/game-images/microgaming/4284/thumbnail.jpg",
    "name": "Pollen Party"
  },
  {
    "value": 4032,
    "icon": "https://d3ejb2l5e3bvmc.cloudfront.net/game-images/microgaming/4285/thumbnail.jpg",
    "name": "Pretty Kitty"
  },
  {
    "value": 4643,
    "icon": "https://d3ejb2l5e3bvmc.cloudfront.net/game-images/microgaming/4286/thumbnail.jpg",
    "name": "Pure Platinum"
  },
  {
    "value": 4486,
    "icon": "https://d3ejb2l5e3bvmc.cloudfront.net/game-images/microgaming/4288/thumbnail.jpg",
    "name": "Queen of the Crystal Rays"
  },
  {
    "value": 2082,
    "icon": "https://d3ejb2l5e3bvmc.cloudfront.net/game-images/microgaming/4289/thumbnail.jpg",
    "name": "Rabbit In The Hat"
  },
  {
    "value": 2361,
    "icon": "https://d3ejb2l5e3bvmc.cloudfront.net/game-images/microgaming/4297/thumbnail.jpg",
    "name": "Reel Gems"
  },
  {
    "value": 3604,
    "icon": "https://d3ejb2l5e3bvmc.cloudfront.net/game-images/microgaming/4300/thumbnail.jpg",
    "name": "Reel Spinner"
  },
  {
    "value": 2831,
    "icon": "https://d3ejb2l5e3bvmc.cloudfront.net/game-images/microgaming/4301/thumbnail.jpg",
    "name": "Reel Strike"
  },
  {
    "value": 3292,
    "icon": "https://d3ejb2l5e3bvmc.cloudfront.net/game-images/microgaming/4302/thumbnail.jpg",
    "name": "Reel Talent"
  },
  {
    "value": 3769,
    "icon": "https://d3ejb2l5e3bvmc.cloudfront.net/game-images/microgaming/4303/thumbnail.jpg",
    "name": "Reel Thunder"
  },
  {
    "value": 4131,
    "icon": "https://d3ejb2l5e3bvmc.cloudfront.net/game-images/microgaming/4304/thumbnail.jpg",
    "name": "Relic Seekers"
  },
  {
    "value": 3487,
    "icon": "https://d3ejb2l5e3bvmc.cloudfront.net/game-images/microgaming/4305/thumbnail.jpg",
    "name": "Retro Reels"
  },
  {
    "value": 4020,
    "icon": "https://d3ejb2l5e3bvmc.cloudfront.net/game-images/microgaming/4306/thumbnail.jpg",
    "name": "Retro Reels - Diamond Glitz"
  },
  {
    "value": 3186,
    "icon": "https://d3ejb2l5e3bvmc.cloudfront.net/game-images/microgaming/4307/thumbnail.jpg",
    "name": "Retro Reels - Extreme Heat"
  },
  {
    "value": 3896,
    "icon": "https://d3ejb2l5e3bvmc.cloudfront.net/game-images/microgaming/4308/thumbnail.jpg",
    "name": "Rhyming Reels Georgie Porgie"
  },
  {
    "value": 3150,
    "icon": "https://d3ejb2l5e3bvmc.cloudfront.net/game-images/microgaming/4309/thumbnail.jpg",
    "name": "Rhyming Reels Hearts And Tarts"
  },
  {
    "value": 2506,
    "icon": "https://d3ejb2l5e3bvmc.cloudfront.net/game-images/microgaming/4311/thumbnail.jpg",
    "name": "Romanov Riches"
  },
  {
    "value": 4018,
    "icon": "https://d3ejb2l5e3bvmc.cloudfront.net/game-images/microgaming/4314/thumbnail.jpg",
    "name": "Rugby Star"
  },
  {
    "value": 4901,
    "icon": "https://d3ejb2l5e3bvmc.cloudfront.net/game-images/microgaming/4316/thumbnail.jpg",
    "name": "Santa Paws"
  },
  {
    "value": 3824,
    "icon": "https://d3ejb2l5e3bvmc.cloudfront.net/game-images/microgaming/4317/thumbnail.jpg",
    "name": "Santa's Wild Ride"
  },
  {
    "value": 3828,
    "icon": "https://d3ejb2l5e3bvmc.cloudfront.net/game-images/microgaming/4318/thumbnail.jpg",
    "name": "Scrooge"
  },
  {
    "value": 4841,
    "icon": "https://d3ejb2l5e3bvmc.cloudfront.net/game-images/microgaming/4319/thumbnail.jpg",
    "name": "Secret Admirer"
  },
  {
    "value": 2592,
    "icon": "https://d3ejb2l5e3bvmc.cloudfront.net/game-images/microgaming/4320/thumbnail.jpg",
    "name": "Secret Romance"
  },
  {
    "value": 4712,
    "icon": "https://d3ejb2l5e3bvmc.cloudfront.net/game-images/microgaming/4322/thumbnail.jpg",
    "name": "Serengeti Gold"
  },
  {
    "value": 2582,
    "icon": "https://d3ejb2l5e3bvmc.cloudfront.net/game-images/microgaming/4323/thumbnail.jpg",
    "name": "Shamrock Holmes Megaways™"
  },
  {
    "value": 3533,
    "icon": "https://d3ejb2l5e3bvmc.cloudfront.net/game-images/microgaming/4324/thumbnail.jpg",
    "name": "Shanghai Beauty"
  },
  {
    "value": 2633,
    "icon": "https://d3ejb2l5e3bvmc.cloudfront.net/game-images/microgaming/4325/thumbnail.jpg",
    "name": "Sherlock Of London Online Slot"
  },
  {
    "value": 4706,
    "icon": "https://d3ejb2l5e3bvmc.cloudfront.net/game-images/microgaming/4327/thumbnail.jpg",
    "name": "Showdown Saloon"
  },
  {
    "value": 4748,
    "icon": "https://d3ejb2l5e3bvmc.cloudfront.net/game-images/microgaming/4329/thumbnail.jpg",
    "name": "Silver Fang"
  },
  {
    "value": 2018,
    "icon": "https://d3ejb2l5e3bvmc.cloudfront.net/game-images/microgaming/4330/thumbnail.jpg",
    "name": "Silver Lioness 4x"
  },
  {
    "value": 2045,
    "icon": "https://d3ejb2l5e3bvmc.cloudfront.net/game-images/microgaming/4331/thumbnail.jpg",
    "name": "Silver Seas"
  },
  {
    "value": 3201,
    "icon": "https://d3ejb2l5e3bvmc.cloudfront.net/game-images/microgaming/4332/thumbnail.jpg",
    "name": "Silverback Multiplier Mountain"
  },
  {
    "value": 2521,
    "icon": "https://d3ejb2l5e3bvmc.cloudfront.net/game-images/microgaming/4334/thumbnail.jpg",
    "name": "Six Acrobats"
  },
  {
    "value": 3391,
    "icon": "https://d3ejb2l5e3bvmc.cloudfront.net/game-images/microgaming/4335/thumbnail.jpg",
    "name": "So Many Monsters"
  },
  {
    "value": 4986,
    "icon": "https://d3ejb2l5e3bvmc.cloudfront.net/game-images/microgaming/4336/thumbnail.jpg",
    "name": "So Much Candy"
  },
  {
    "value": 2365,
    "icon": "https://d3ejb2l5e3bvmc.cloudfront.net/game-images/microgaming/4337/thumbnail.jpg",
    "name": "So Much Sushi"
  },
  {
    "value": 2377,
    "icon": "https://d3ejb2l5e3bvmc.cloudfront.net/game-images/microgaming/4338/thumbnail.jpg",
    "name": "Soccer Striker"
  },
  {
    "value": 2819,
    "icon": "https://d3ejb2l5e3bvmc.cloudfront.net/game-images/microgaming/4339/thumbnail.jpg",
    "name": "Solar Wilds"
  },
  {
    "value": 2501,
    "icon": "https://d3ejb2l5e3bvmc.cloudfront.net/game-images/microgaming/4341/thumbnail.jpg",
    "name": "Spring Break"
  },
  {
    "value": 3613,
    "icon": "https://d3ejb2l5e3bvmc.cloudfront.net/game-images/microgaming/4342/thumbnail.jpg",
    "name": "Squealin' Riches"
  },
  {
    "value": 2955,
    "icon": "https://d3ejb2l5e3bvmc.cloudfront.net/game-images/microgaming/4344/thumbnail.jpg",
    "name": "Starlight Kiss"
  },
  {
    "value": 2064,
    "icon": "https://d3ejb2l5e3bvmc.cloudfront.net/game-images/microgaming/4345/thumbnail.jpg",
    "name": "Stash of the Titans"
  },
  {
    "value": 3502,
    "icon": "https://d3ejb2l5e3bvmc.cloudfront.net/game-images/microgaming/4346/thumbnail.jpg",
    "name": "Sterling Silver"
  },
  {
    "value": 3651,
    "icon": "https://d3ejb2l5e3bvmc.cloudfront.net/game-images/microgaming/4347/thumbnail.jpg",
    "name": "Sugar Parade"
  },
  {
    "value": 3355,
    "icon": "https://d3ejb2l5e3bvmc.cloudfront.net/game-images/microgaming/4348/thumbnail.jpg",
    "name": "Summer Holiday"
  },
  {
    "value": 2650,
    "icon": "https://d3ejb2l5e3bvmc.cloudfront.net/game-images/microgaming/4349/thumbnail.jpg",
    "name": "Summertime"
  },
  {
    "value": 3428,
    "icon": "https://d3ejb2l5e3bvmc.cloudfront.net/game-images/microgaming/4351/thumbnail.jpg",
    "name": "SunTide"
  },
  {
    "value": 3519,
    "icon": "https://d3ejb2l5e3bvmc.cloudfront.net/game-images/microgaming/4354/thumbnail.jpg",
    "name": "Tally Ho"
  },
  {
    "value": 4450,
    "icon": "https://d3ejb2l5e3bvmc.cloudfront.net/game-images/microgaming/4355/thumbnail.jpg",
    "name": "Tarzan"
  },
  {
    "value": 4743,
    "icon": "https://d3ejb2l5e3bvmc.cloudfront.net/game-images/microgaming/4356/thumbnail.jpg",
    "name": "TARZAN® and the Jewels of Opar"
  },
  {
    "value": 2755,
    "icon": "https://d3ejb2l5e3bvmc.cloudfront.net/game-images/microgaming/4359/thumbnail.jpg",
    "name": "The Finer Reels of Life"
  },
  {
    "value": 3849,
    "icon": "https://d3ejb2l5e3bvmc.cloudfront.net/game-images/microgaming/4362/thumbnail.jpg",
    "name": "The Grand Journey"
  },
  {
    "value": 3300,
    "icon": "https://d3ejb2l5e3bvmc.cloudfront.net/game-images/microgaming/4363/thumbnail.jpg",
    "name": "The Great Albini"
  },
  {
    "value": 2781,
    "icon": "https://d3ejb2l5e3bvmc.cloudfront.net/game-images/microgaming/4364/thumbnail.jpg",
    "name": "The Heat Is On"
  },
  {
    "value": 4545,
    "icon": "https://d3ejb2l5e3bvmc.cloudfront.net/game-images/microgaming/4367/thumbnail.jpg",
    "name": "The Phantom of the Opera"
  },
  {
    "value": 3310,
    "icon": "https://d3ejb2l5e3bvmc.cloudfront.net/game-images/microgaming/4369/thumbnail.jpg",
    "name": "The Twisted Circus"
  },
  {
    "value": 3465,
    "icon": "https://d3ejb2l5e3bvmc.cloudfront.net/game-images/microgaming/4370/thumbnail.jpg",
    "name": "Thunderstruck"
  },
  {
    "value": 4688,
    "icon": "https://d3ejb2l5e3bvmc.cloudfront.net/game-images/microgaming/4371/thumbnail.jpg",
    "name": "ThunderStruck II"
  },
  {
    "value": 3470,
    "icon": "https://d3ejb2l5e3bvmc.cloudfront.net/game-images/microgaming/4374/thumbnail.jpg",
    "name": "Tiger's Eye"
  },
  {
    "value": 3919,
    "icon": "https://d3ejb2l5e3bvmc.cloudfront.net/game-images/microgaming/4375/thumbnail.jpg",
    "name": "Tiki Reward"
  },
  {
    "value": 2211,
    "icon": "https://d3ejb2l5e3bvmc.cloudfront.net/game-images/microgaming/4376/thumbnail.jpg",
    "name": "Tiki Vikings"
  },
  {
    "value": 4024,
    "icon": "https://d3ejb2l5e3bvmc.cloudfront.net/game-images/microgaming/4379/thumbnail.jpg",
    "name": "Tomb Raider"
  },
  {
    "value": 4098,
    "icon": "https://d3ejb2l5e3bvmc.cloudfront.net/game-images/microgaming/4382/thumbnail.jpg",
    "name": "Treasure Palace"
  },
  {
    "value": 4789,
    "icon": "https://d3ejb2l5e3bvmc.cloudfront.net/game-images/microgaming/4384/thumbnail.jpg",
    "name": "Untamed - Giant Panda"
  },
  {
    "value": 2994,
    "icon": "https://d3ejb2l5e3bvmc.cloudfront.net/game-images/microgaming/4391/thumbnail.jpg",
    "name": "Village People Macho Moves"
  },
  {
    "value": 2563,
    "icon": "https://d3ejb2l5e3bvmc.cloudfront.net/game-images/microgaming/4392/thumbnail.jpg",
    "name": "Vinyl Countdown"
  },
  {
    "value": 2903,
    "icon": "https://d3ejb2l5e3bvmc.cloudfront.net/game-images/microgaming/4393/thumbnail.jpg",
    "name": "Voila!"
  },
  {
    "value": 4326,
    "icon": "https://d3ejb2l5e3bvmc.cloudfront.net/game-images/microgaming/4394/thumbnail.jpg",
    "name": "Wacky Panda"
  },
  {
    "value": 3955,
    "icon": "https://d3ejb2l5e3bvmc.cloudfront.net/game-images/microgaming/4395/thumbnail.jpg",
    "name": "Wanted Outlaws"
  },
  {
    "value": 3976,
    "icon": "https://d3ejb2l5e3bvmc.cloudfront.net/game-images/microgaming/4396/thumbnail.jpg",
    "name": "Western Gold"
  },
  {
    "value": 2281,
    "icon": "https://d3ejb2l5e3bvmc.cloudfront.net/game-images/microgaming/4397/thumbnail.jpg",
    "name": "What A Hoot"
  },
  {
    "value": 3152,
    "icon": "https://d3ejb2l5e3bvmc.cloudfront.net/game-images/microgaming/4398/thumbnail.png",
    "name": "Wheel of Winners"
  },
  {
    "value": 3264,
    "icon": "https://d3ejb2l5e3bvmc.cloudfront.net/game-images/microgaming/4399/thumbnail.jpg",
    "name": "Wicked Tales: Dark Red"
  },
  {
    "value": 3243,
    "icon": "https://d3ejb2l5e3bvmc.cloudfront.net/game-images/microgaming/4400/thumbnail.jpg",
    "name": "Wild Catch (New)"
  },
  {
    "value": 4343,
    "icon": "https://d3ejb2l5e3bvmc.cloudfront.net/game-images/microgaming/4401/thumbnail.jpg",
    "name": "Wild Orient"
  },
  {
    "value": 2897,
    "icon": "https://d3ejb2l5e3bvmc.cloudfront.net/game-images/microgaming/4402/thumbnail.jpg",
    "name": "Wild Scarabs"
  },
  {
    "value": 2843,
    "icon": "https://d3ejb2l5e3bvmc.cloudfront.net/game-images/microgaming/4405/thumbnail.jpg",
    "name": "Zombie Hoard"
  },
  {
    "value": 2204,
    "icon": "https://d3ejb2l5e3bvmc.cloudfront.net/game-images/microgaming/4616/thumbnail.jpg",
    "name": "25000 Talons"
  },
  {
    "value": 2434,
    "icon": "https://d3ejb2l5e3bvmc.cloudfront.net/game-images/microgaming/4617/thumbnail.jpg",
    "name": "Cash 'N Riches Megaways"
  },
  {
    "value": 2646,
    "icon": "https://d3ejb2l5e3bvmc.cloudfront.net/game-images/microgaming/4618/thumbnail.jpg",
    "name": "The Great Albini 2"
  },
  {
    "value": 4324,
    "icon": "https://d3ejb2l5e3bvmc.cloudfront.net/game-images/microgaming/4580/thumbnail.jpg",
    "name": "Dungeons and Diamonds™"
  },
  {
    "value": 2183,
    "icon": "https://d3ejb2l5e3bvmc.cloudfront.net/game-images/microgaming/4620/thumbnail.jpg",
    "name": "Masters of Valhalla"
  },
  {
    "value": 4707,
    "icon": "https://d3ejb2l5e3bvmc.cloudfront.net/game-images/microgaming/4615/thumbnail.jpg",
    "name": "Western Gold 2"
  },
  {
    "value": 4211,
    "icon": "https://d3ejb2l5e3bvmc.cloudfront.net/game-images/microgaming/4619/thumbnail.jpg",
    "name": "Aztec Falls"
  },
  {
    "value": 3366,
    "icon": "https://d3ejb2l5e3bvmc.cloudfront.net/game-images/microgaming/4709/thumbnail.jpg",
    "name": "Wild Wild Romance"
  },
  {
    "value": 4404,
    "icon": "https://d3ejb2l5e3bvmc.cloudfront.net/game-images/microgaming/4710/thumbnail.jpg",
    "name": "Wildfire Wins"
  },
  {
    "value": 2071,
    "icon": "https://d3ejb2l5e3bvmc.cloudfront.net/game-images/microgaming/4711/thumbnail.jpg",
    "name": "AbraCatDabra™"
  },
  {
    "value": 4460,
    "icon": "https://d3ejb2l5e3bvmc.cloudfront.net/game-images/microgaming/4712/thumbnail.jpg",
    "name": "Match Day"
  },
  {
    "value": 4042,
    "icon": "https://d3ejb2l5e3bvmc.cloudfront.net/game-images/microgaming/4713/thumbnail.jpg",
    "name": "Lightning Fortunes"
  },
  {
    "value": 2132,
    "icon": "https://d3ejb2l5e3bvmc.cloudfront.net/game-images/microgaming/4707/thumbnail.jpg",
    "name": "Día del Mariachi Megaways™"
  },
  {
    "value": 2980,
    "icon": "https://d3ejb2l5e3bvmc.cloudfront.net/game-images/microgaming/4708/thumbnail.jpg",
    "name": "Circus Jugglers Jackpots"
  },
  {
    "value": 2494,
    "icon": "https://d3ejb2l5e3bvmc.cloudfront.net/game-images/microgaming/4727/thumbnail.jpg",
    "name": "Lucky Leprechaun Clusters"
  },
  {
    "value": 3658,
    "icon": "https://d3ejb2l5e3bvmc.cloudfront.net/game-images/microgaming/4728/thumbnail.jpg",
    "name": "Divine Riches Helios"
  },
  {
    "value": 2510,
    "icon": "https://d3ejb2l5e3bvmc.cloudfront.net/game-images/microgaming/4729/thumbnail.jpg",
    "name": "Immortal Romance Video Bingo"
  }
]